LICENSE
MANIFEST.in
README.rst
setup.cfg
setup.py
django_slack_logger/__init__.py
django_slack_logger/admin.py
django_slack_logger/apps.py
django_slack_logger/logger.py
django_slack_logger/models.py
django_slack_logger/tests.py
django_slack_logger/views.py
django_slack_logger.egg-info/PKG-INFO
django_slack_logger.egg-info/SOURCES.txt
django_slack_logger.egg-info/dependency_links.txt
django_slack_logger.egg-info/top_level.txt
django_slack_logger/migrations/__init__.py